Workbook

Sheet Mortality_Table 
A1: Age | B1: Actual Deaths | C1: Policies Exposed | D1: Actual_qx | E1: Expected_qx 2015 | F1: A/E_Ratio
A2: 25 | B2: 22 | C2: 67370.9 | D2: 0.00032655048 | E2: 0.00024530992 | F2: 1.3311752
A3: 26 | B3: 26 | C3: 79744.28 | D3: 0.0003260422 | E3: 0.00021636599 | F3: 1.5069013
A4: 27 | B4: 28 | C4: 95809.006 | D4: 0.0002922481 | E4: 0.00019785082 | F4: 1.4771134
A5: 28 | B5: 19 | C5: 112756.79 | D5: 0.00016850426 | E5: 0.00018627401 | F5: 0.90460425
A6: 29 | B6: 37 | C6: 134288.28 | D6: 0.00027552666 | E6: 0.00018199556 | F6: 1.5139197
A7: 30 | B7: 49 | C7: 162515.47 | D7: 0.00030150977 | E7: 0.00018411725 | F7: 1.6375965
A8: 31 | B8: 73 | C8: 200930.29 | D8: 0.00036331008 | E8: 0.00018970987 | F8: 1.9150826
A9: 32 | B9: 74 | C9: 226761.02 | D9: 0.00032633475 | E9: 0.00019525728 | F9: 1.6713064
A10: 33 | B10: 84 | C10: 240316.26 | D10: 0.00034953939 | E10: 0.0002064219 | F10: 1.6933251
A11: 34 | B11: 72 | C11: 251155.08 | D11: 0.00028667546 | E11: 0.00022533456 | F11: 1.2722215
A12: 35 | B12: 92 | C12: 271480.6 | D12: 0.0003388824 | E12: 0.00024617107 | F12: 1.3766135
A13: 36 | B13: 118 | C13: 290036.14 | D13: 0.00040684585 | E13: 0.00027591427 | F13: 1.4745372
... A52: 75 | B52: 551 | C52: 27489.457 | D52: 0.020044048 | E52: 0.014051121 | F52: 1.4265088

Sheet Assumptions
A1: Economic Assumptions
A2: Annual Interest Rate | B2: 0.05
A3: Annual Lapse Rate | B3: 0.03
A4: Policy Assumptions
A5: Policy Term (Years) | B5: 20
A6: Face Amount ($) | B6: 500000
A7: Issue Age | B7: 35
A8: Expense Assumptions
A9: Per Policy Annual Expense ($) | B9: all
A10: Expense Loading (% of premium) | B10: 0.15
A11: Profit Margin (% of premium) | B11: 0.1

Sheet Premium Calculator
A1: Policy Year | B1: Attained Age | C1: Survivors | D1: Deaths | E1: Death Claims | F1: Premium Income | G1: Discount Factor | H1: PV_Net_Cost
A2: 1 | B2: =Assumptions!$B$7+A2-1 -> 35 | C2: =1000 -> 1000 | D2: =C2*VLOOKUP(B2,'Mortality_Table '!A:D,4,FALSE) -> 0.3388824 | E2: =D2*Assumptions!$B$6 -> 169441.2 | F2: =C2*$K$2*G2 -> 349900.4 | G2: =1/(1+Assumptions!$B$2)^A2 -> 0.95238095 | H2: =E2*G2 -> 161372.57 | J2: Annual Premium | K2: 367.39542
A3: 2 | B3: =Assumptions!$B$7+A3-1 -> 36 | C3: =C2*(1-VLOOKUP(B2,'Mortality_Table '!$A:$D,4,FALSE))*(1-Assumptions!$B$3) -> 969.67128 | D3: =C3*VLOOKUP(B3,'Mortality_Table '!A:D,4,FALSE) -> 0.39450674 | E3: =D3*Assumptions!$B$6 -> 197253.37 | F3: =C3*$K$2*G3 -> 323131.78 | G3: =1/(1+Assumptions!$B$2)^A3 -> 0.90702948 | H3: =E3*G3 -> 178914.62
A4: 3 | B4: =Assumptions!$B$7+A4-1 -> 37 | C4: =C3*(1-VLOOKUP(B3,'Mortality_Table '!$A:$D,4,FALSE))*(1-Assumptions!$B$3) -> 940.19847 | D4: =C4*VLOOKUP(B4,'Mortality_Table '!A:D,4,FALSE) -> 0.42906917 | E4: =D4*Assumptions!$B$6 -> 214534.59 | F4: =C4*$K$2*G4 -> 298390.77 | G4: =1/(1+Assumptions!$B$2)^A4 -> 0.8638376 | H4: =E4*G4 -> 185323.04 | J4: Gross Annual Premium | K4: =K2/(1-Assumptions!$B$10-Assumptions!$B$11) -> 489.86056
A5: 4 | B5: =Assumptions!$B$7+A5-1 -> 38 | C5: =C4*(1-VLOOKUP(B4,'Mortality_Table '!$A:$D,4,FALSE))*(1-Assumptions!$B$3) -> 911.57632 | D5: =C5*VLOOKUP(B5,'Mortality_Table '!A:D,4,FALSE) -> 0.39896622 | E5: =D5*Assumptions!$B$6 -> 199483.11 | F5: =C5*$K$2*G5 -> 275530.43 | G5: =1/(1+Assumptions!$B$2)^A5 -> 0.82270247 | H5: =E5*G5 -> 164115.25
A6: 5 | B6: =Assumptions!$B$7+A6-1 -> 39 | C6: =C5*(1-VLOOKUP(B5,'Mortality_Table '!$A:$D,4,FALSE))*(1-Assumptions!$B$3) -> 883.84204 | D6: =C6*VLOOKUP(B6,'Mortality_Table '!A:D,4,FALSE) -> 0.42878883 | E6: =D6*Assumptions!$B$6 -> 214394.42 | F6: =C6*$K$2*G6 -> 254426.24 | G6: =1/(1+Assumptions!$B$2)^A6 -> 0.78352617 | H6: =E6*G6 -> 167983.63 | J6: Monthly Premium | K6: =K4/12 -> 40.821713
A7: 6 | B7: =Assumptions!$B$7+A7-1 -> 40 | C7: =C6*(1-VLOOKUP(B6,'Mortality_Table '!$A:$D,4,FALSE))*(1-Assumptions!$B$3) -> 856.91085 | D7: =C7*VLOOKUP(B7,'Mortality_Table '!A:D,4,FALSE) -> 0.52357348 | E7: =D7*Assumptions!$B$6 -> 261786.74 | F7: =C7*$K$2*G7 -> 234927.35 | G7: =1/(1+Assumptions!$B$2)^A7 -> 0.7462154 | H7: =E7*G7 -> 195349.3
A8: 7 | B8: =Assumptions!$B$7+A8-1 -> 41 | C8: =C7*(1-VLOOKUP(B7,'Mortality_Table '!$A:$D,4,FALSE))*(1-Assumptions!$B$3) -> 830.69566 | D8: =C8*VLOOKUP(B8,'Mortality_Table '!A:D,4,FALSE) -> 0.40301943 | E8: =D8*Assumptions!$B$6 -> 201509.72 | F8: =C8*$K$2*G8 -> 216895.52 | G8: =1/(1+Assumptions!$B$2)^A8 -> 0.71068133 | H8: =E8*G8 -> 143209.19
A9: 8 | B9: =Assumptions!$B$7+A9-1 -> 42 | C9: =C8*(1-VLOOKUP(B8,'Mortality_Table '!$A:$D,4,FALSE))*(1-Assumptions!$B$3) -> 805.38386 | D9: =C9*VLOOKUP(B9,'Mortality_Table '!A:D,4,FALSE) -> 0.46632837 | E9: =D9*Assumptions!$B$6 -> 233164.19 | F9: =C9*$K$2*G9 -> 200272.94 | G9: =1/(1+Assumptions!$B$2)^A9 -> 0.67683936 | H9: =E9*G9 -> 157814.7
A10: 9 | B10: =Assumptions!$B$7+A10-1 -> 43 | C10: =C9*(1-VLOOKUP(B9,'Mortality_Table '!$A:$D,4,FALSE))*(1-Assumptions!$B$3) -> 780.77 | D10: =C10*VLOOKUP(B10,'Mortality_Table '!A:D,4,FALSE) -> 0.5337573 | E10: =D10*Assumptions!$B$6 -> 266878.65 | F10: =C10*$K$2*G10 -> 184906.92 | G10: =1/(1+Assumptions!$B$2)^A10 -> 0.64460892 | H10: =E10*G10 -> 172032.36
A11: 10 | B11: =Assumptions!$B$7+A11-1 -> 44 | C11: =C10*(1-VLOOKUP(B10,'Mortality_Table '!$A:$D,4,FALSE))*(1-Assumptions!$B$3) -> 756.82916 | D11: =C11*VLOOKUP(B11,'Mortality_Table '!A:D,4,FALSE) -> 0.65032121 | E11: =D11*Assumptions!$B$6 -> 325160.6 | F11: =C11*$K$2*G11 -> 170702 | G11: =1/(1+Assumptions!$B$2)^A11 -> 0.61391325 | H11: =E11*G11 -> 199620.4
A12: 11 | B12: =Assumptions!$B$7+A12-1 -> 45 | C12: =C11*(1-VLOOKUP(B11,'Mortality_Table '!$A:$D,4,FALSE))*(1-Assumptions!$B$3) -> 733.49347 | D12: =C12*VLOOKUP(B12,'Mortality_Table '!A:D,4,FALSE) -> 0.67338602 | E12: =D12*Assumptions!$B$6 -> 336693.01 | F12: =C12*$K$2*G12 -> 157560.63 | G12: =1/(1+Assumptions!$B$2)^A12 -> 0.58467929 | H12: =E12*G12 -> 196857.43
A13: 12 | B13: =Assumptions!$B$7+A13-1 -> 46 | C13: =C12*(1-VLOOKUP(B12,'Mortality_Table '!$A:$D,4,FALSE))*(1-Assumptions!$B$3) -> 710.83549 | D13: =C13*VLOOKUP(B13,'Mortality_Table '!A:D,4,FALSE) -> 0.69270772 | E13: =D13*Assumptions!$B$6 -> 346353.86 | F13: =C13*$K$2*G13 -> 145422.38 | G13: =1/(1+Assumptions!$B$2)^A13 -> 0.55683742 | H13: =E13*G13 -> 192862.79
A14: 13 | B14: =Assumptions!$B$7+A14-1 -> 47 | C14: =C13*(1-VLOOKUP(B13,'Mortality_Table '!$A:$D,4,FALSE))*(1-Assumptions!$B$3) -> 688.83849 | D14: =C14*VLOOKUP(B14,'Mortality_Table '!A:D,4,FALSE) -> 0.63119683 | E14: =D14*Assumptions!$B$6 -> 315598.41 | F14: =C14*$K$2*G14 -> 134211.66 | G14: =1/(1+Assumptions!$B$2)^A14 -> 0.53032135 | H14: =E14*G14 -> 167368.58
A15: 14 | B15: =Assumptions!$B$7+A15-1 -> 48 | C15: =C14*(1-VLOOKUP(B14,'Mortality_Table '!$A:$D,4,FALSE))*(1-Assumptions!$B$3) -> 667.56108 | D15: =C15*VLOOKUP(B15,'Mortality_Table '!A:D,4,FALSE) -> 0.74543756 | E15: =D15*Assumptions!$B$6 -> 372718.78 | F15: =C15*$K$2*G15 -> 123872.4 | G15: =1/(1+Assumptions!$B$2)^A15 -> 0.50506795 | H15: =E15*G15 -> 188248.31
A16: 15 | B16: =Assumptions!$B$7+A16-1 -> 49 | C16: =C15*(1-VLOOKUP(B15,'Mortality_Table '!$A:$D,4,FALSE))*(1-Assumptions!$B$3) -> 646.81117 | D16: =C16*VLOOKUP(B16,'Mortality_Table '!A:D,4,FALSE) -> 0.7514845 | E16: =D16*Assumptions!$B$6 -> 375742.25 | F16: =C16*$K$2*G16 -> 114306.72 | G16: =1/(1+Assumptions!$B$2)^A16 -> 0.4810171 | H16: =E16*G16 -> 180738.45
A17: 16 | B17: =Assumptions!$B$7+A17-1 -> 50 | C17: =C16*(1-VLOOKUP(B16,'Mortality_Table '!$A:$D,4,FALSE))*(1-Assumptions!$B$3) -> 626.6779 | D17: =C17*VLOOKUP(B17,'Mortality_Table '!A:D,4,FALSE) -> 0.8057667 | E17: =D17*Assumptions!$B$6 -> 402883.35 | F17: =C17*$K$2*G17 -> 105474.95 | G17: =1/(1+Assumptions!$B$2)^A17 -> 0.45811152 | H17: =E17*G17 -> 184565.5
A18: 17 | B18: =Assumptions!$B$7+A18-1 -> 51 | C18: =C17*(1-VLOOKUP(B17,'Mortality_Table '!$A:$D,4,FALSE))*(1-Assumptions!$B$3) -> 607.09597 | D18: =C18*VLOOKUP(B18,'Mortality_Table '!A:D,4,FALSE) -> 0.83725933 | E18: =D18*Assumptions!$B$6 -> 418629.66 | F18: =C18*$K$2*G18 -> 97313.479 | G18: =1/(1+Assumptions!$B$2)^A18 -> 0.43629669 | H18: =E18*G18 -> 182646.74
... A21: 20 | B21: =Assumptions!$B$7+A21-1 -> 54 | C21: =C20*(1-VLOOKUP(B20,'Mortality_Table '!$A:$D,4,FALSE))*(1-Assumptions!$B$3) -> 551.39043 | D21: =C21*VLOOKUP(B21,'Mortality_Table '!A:D,4,FALSE) -> 1.1105106 | E21: =D21*Assumptions!$B$6 -> 555255.31 | F21: =C21*$K$2*G21 -> 76349.638 | G21: =1/(1+Assumptions!$B$2)^A21 -> 0.37688948 | H21: =E21*G21 -> 209269.89
F23: Total PV Premiums | H23: Total PV Claims
F24: =SUM(F2:F21) -> 3636171.9 | H24: =SUM(H2:H21) -> 3636181.8

Sheet Dashboard
